wimpy/__init__.py
wimpy/compat.py
wimpy/exceptions.py
wimpy/util.py
wimpy-0.6.dist-info/METADATA
wimpy-0.6.dist-info/RECORD
wimpy-0.6.dist-info/WHEEL
wimpy-0.6.dist-info/top_level.txt
