Metadata-Version: 2.1
Name: wimpy
Version: 0.6
Summary: Anti-copy-pasta
Home-page: https://github.com/wimglenn/wimpy
Author: Wim Glenn
Author-email: hey@wimglenn.com
License: MIT
Platform: UNKNOWN
License-File: LICENSE
